{
  "name": "radiant_quartz",
  "tool": {
    "head": {
      "attackDamage": 8,
      "speed": 12,
      "durability": 1000,
      "harvestLevel": 3
    },
    "handle": {
      "modifier": 0.3,
      "durability": -200
    },
    "extra": {
        "durability": 0
    },
    "bow": {
        "speed": 0.6,
        "range": 1.8,
        "bonusDamage": -1
    }
  },
  "color": "#f9bef3",
  "craftable": true,
  "madeInToolForge": false,
  "createMeltingRecipes": false,
  "meltingTemperature": 720,
  "looks": {
    "shininess": 0.8,
    "brightness": 0.25,
    "hueshift": -0.1
  },
  "fluid": {
    "viscosity": 8000,
    "density": 1500,
    "temperature": 1000,
    "luminosity": 8
  },
  "oreDictSuffixes": [],
  "matParts": [
    "HEAD",
    "HANDLE",
    "EXTRA",
    "BOW",
    "CORE",
    "PLATES",
    "TRIM"
  ],
  "nameLocales": {
    "en_us": "Radiant Quartz",
    "zh_cn": "已雕琢辉耀石英"
  },
  "smeltingItems": {
    "ingot": [
      "arcanearchives:shaped_quartz"
    ],
    "block": [
    ],
    "nugget": [
    ],
    "ore": [
    ],
    "dust": [
    ],
    "plate": [
    ],
    "gear": [
    ]
  },
  "smeltingTags": {
    "ingot": [],
    "block": [],
    "nugget": [],
    "ore": [],
    "dust": [],
    "plate": [],
    "gear": []
  },
  "armor": {
    "core": {
      "defense": 7,
      "durability": 0
    },
    "plates": {
      "toughness": 3,
      "modifier": 0.5,
      "durability": 1
    },
    "trim": {
      "extraDurability": 1.3
    }
  },
  "specificTraits": {
    "HEAD": [
      "crystal_force",
      "tconevo.culling"
    ],
    "HANDLE": [
      "crystal_force",
      "perfectionist"
    ],
    "EXTRA": [
      "crystal_force",
      "shocking"
    ],
    "BOW": [
      "crystal_force",
      "tconevo.culling"
    ],
    "CORE": [
      "indomitable_armor",
      "alien_armor"
    ],
    "PLATES": [
      "true_defense_armor",
      "tconevo.superdense_armor"
    ],
    "TRIM": [
      "prideful_armor",
      "diffuse_reflecting_armor"
    ]
  }
}