[
    {
        "dimension": 111,
        "mobs": [
            {
                "mob": "headcrumbs:human",
                "weight": 5,
                "groupcountmin": 1,
                "groupcountmax": 3
            }
        ]
    },
	 {
        "dimension": 0,
		"biome": [
			"abyssalcraft:darklands",
			"abyssalcraft:darklands_forest",
			"abyssalcraft:darklands_mountain",
			"abyssalcraft:darklands_hills",
			"abyssalcraft:darklands_plains"
		],
        "mobs": [
            {
                "mob": "abyssalcraft:shadowmonster",
                "weight": 5,
                "groupcountmin": 1,
                "groupcountmax": 2
            }
        ]
    },
	{
        "dimension": 0,
		"biometype": [
			"OCEAN"
		],
        "mobs": [
            {
                "mob": "minecraft:guardian",
                "weight": 4,
                "groupcountmin": 1,
                "groupcountmax": 3
            }
        ]
    },
    {
        "dimension": 42,
        "mobs": [
            {
                "mob": "iceandfire:if_pixie",
                "weight": 12,
                "groupcountmin": 2,
                "groupcountmax": 4
            },
            {
                "mob": "aether_legacy:phyg",
                "weight": 5,
                "groupcountmin": 4,
                "groupcountmax": 6
            },
            {
                "mob": "aether_legacy:sheepuff",
                "weight": 5,
                "groupcountmin": 4,
                "groupcountmax": 6
            },
            {
                "mob": "aether_legacy:flying_cow",
                "weight": 5,
                "groupcountmin": 4,
                "groupcountmax": 6
            },
            {
                "mob": "quark:stoneling",
                "weight": 2,
                "groupcountmin": 2,
                "groupcountmax": 5
            }
        ]
    },
    {
        "dimension": 42,
        "biome": [
            "gct_mobs:alfheim_forest"
        ],
        "mobs": [
            {
                "mob": "gct_mobs:elf",
                "weight": 3,
                "groupcountmin": 2,
                "groupcountmax": 4
            }
        ]
    },
    {
        "dimension": 42,
        "biome": [
            "gct_mobs:reversed_forest"
        ],
        "mobs": [
            {
                "mob": "gct_mobs:reversed_elf",
                "weight": 5,
                "groupcountmin": 3,
                "groupcountmax": 5
            }
        ]
    },
    {
        "dimension": 42,
        "biome": [
            "gct_mobs:alfheim_hill"
        ],
        "mobs": [
            {
                "mob": "twilightforest:stable_ice_core",
                "weight": 4,
                "groupcountmin": 1,
                "groupcountmax": 3
            }
        ]
    },
    {
        "dimension": 78,
        "mobs": [
            {
                "mob": "minecraft:blaze",
                "weight": 8,
                "groupcountmin": 1,
                "groupcountmax": 2
            },
            {
                "mob": "thermalfoundation:blizz",
                "weight": 8,
                "groupcountmin": 1,
                "groupcountmax": 2
            },
            {
                "mob": "thermalfoundation:basalz",
                "weight": 8,
                "groupcountmin": 1,
                "groupcountmax": 2
            },
            {
                "mob": "thermalfoundation:blitz",
                "weight": 8,
                "groupcountmin": 1,
                "groupcountmax": 2
            }
        ]
    },
    {
        "dimension": 41,
        "mobs": [
            {
                "mob": "natura:imp",
                "weight": 5,
                "groupcountmin": 3,
                "groupcountmax": 6
            },
            {
                "mob": "abyssalcraft:demonpig",
                "weight": 5,
                "groupcountmin": 2,
                "groupcountmax": 4
            },
            {
                "mob": "abyssalcraft:demoncow",
                "weight": 5,
                "groupcountmin": 2,
                "groupcountmax": 4
            },
            {
                "mob": "abyssalcraft:demonchicken",
                "weight": 5,
                "groupcountmin": 2,
                "groupcountmax": 4
            },
            {
                "mob": "abyssalcraft:demonsheep",
                "weight": 5,
                "groupcountmin": 2,
                "groupcountmax": 4
            },
            {
                "mob": "thaumcraft:cultistknight",
                "weight": 4,
                "groupcountmin": 1,
                "groupcountmax": 4
            },
            {
                "mob": "thaumcraft:cultistcleric",
                "weight": 4,
                "groupcountmin": 1,
                "groupcountmax": 4
            },
            {
                "mob": "crimsonrevelations:cultist_archer",
                "weight": 4,
                "groupcountmin": 1,
                "groupcountmax": 4
            },
            {
                "mob": "thaumicconcilium:crimson_paladin",
                "weight": 3,
                "groupcountmin": 1,
                "groupcountmax": 2
            }
        ]
    }
]
